mkdocs_juvix/__init__.py
mkdocs_juvix/common/__init__.py
mkdocs_juvix/common/cache.py
mkdocs_juvix/common/models/__init__.py
mkdocs_juvix/common/models/entry.py
mkdocs_juvix/common/models/link.py
mkdocs_juvix/common/models/loc.py
mkdocs_juvix/common/models/wikilink.py
mkdocs_juvix/common/preprocesors/links.py
mkdocs_juvix/common/utils.py
mkdocs_juvix/differ.py
mkdocs_juvix/env.py
mkdocs_juvix/fixtures/isabelle_at_bottom.md
mkdocs_juvix/fixtures/juvix_codeblock_footer.template
mkdocs_juvix/images.py
mkdocs_juvix/juvix_version.py
mkdocs_juvix/links.py
mkdocs_juvix/logger.py
mkdocs_juvix/main.py
mkdocs_juvix/snippets.py
mkdocs_juvix/todos.py
mkdocs_juvix/utils.py
src/__init__.py
src/cli.py
src/fixtures/.gitignore
src/fixtures/.juvix-build/0.6.8/deps/3efa00de03f7065ac7000e54d384ba7907042f73351ad857d538fbe4fe907529/.devcontainer/Dockerfile
src/fixtures/.juvix-build/0.6.8/deps/3efa00de03f7065ac7000e54d384ba7907042f73351ad857d538fbe4fe907529/.devcontainer/devcontainer.json
src/fixtures/.juvix-build/0.6.8/deps/3efa00de03f7065ac7000e54d384ba7907042f73351ad857d538fbe4fe907529/.git/HEAD
src/fixtures/.juvix-build/0.6.8/deps/3efa00de03f7065ac7000e54d384ba7907042f73351ad857d538fbe4fe907529/.git/config
src/fixtures/.juvix-build/0.6.8/deps/3efa00de03f7065ac7000e54d384ba7907042f73351ad857d538fbe4fe907529/.git/description
src/fixtures/.juvix-build/0.6.8/deps/3efa00de03f7065ac7000e54d384ba7907042f73351ad857d538fbe4fe907529/.git/hooks/applypatch-msg.sample
src/fixtures/.juvix-build/0.6.8/deps/3efa00de03f7065ac7000e54d384ba7907042f73351ad857d538fbe4fe907529/.git/hooks/commit-msg.sample
src/fixtures/.juvix-build/0.6.8/deps/3efa00de03f7065ac7000e54d384ba7907042f73351ad857d538fbe4fe907529/.git/hooks/fsmonitor-watchman.sample
src/fixtures/.juvix-build/0.6.8/deps/3efa00de03f7065ac7000e54d384ba7907042f73351ad857d538fbe4fe907529/.git/hooks/post-update.sample
src/fixtures/.juvix-build/0.6.8/deps/3efa00de03f7065ac7000e54d384ba7907042f73351ad857d538fbe4fe907529/.git/hooks/pre-applypatch.sample
mkdocs_juvix_plugin-0.4.9.dist-info/METADATA
mkdocs_juvix_plugin-0.4.9.dist-info/WHEEL
mkdocs_juvix_plugin-0.4.9.dist-info/entry_points.txt
mkdocs_juvix_plugin-0.4.9.dist-info/RECORD
